osrl/__init__.py
osrl/algorithms/__init__.py
osrl/algorithms/bc.py
osrl/algorithms/bcql.py
osrl/algorithms/bearl.py
osrl/algorithms/cdt.py
osrl/algorithms/coptidice.py
osrl/algorithms/cpq.py
osrl/common/__init__.py
osrl/common/dataset.py
osrl/common/exp_util.py
osrl/common/net.py
osrl_lib-0.1.0.dist-info/LICENSE
osrl_lib-0.1.0.dist-info/METADATA
osrl_lib-0.1.0.dist-info/WHEEL
osrl_lib-0.1.0.dist-info/top_level.txt
osrl_lib-0.1.0.dist-info/RECORD
