Metadata-Version: 2.1
Name: osrl-lib
Version: 0.1.0
Summary: Elegant Implementations of Offline Safe Reinforcement Learning Algorithms
Home-page: https://github.com/liuzuxin/offline-safe-rl-baselines.git
Author: Zijian Guo; Zuxin Liu
Author-email: zuxin1997@gmail.com
License: MIT
Keywords: offline safe reinforcement learning algorithms pytorch
Classifier: Development Status :: 3 - Alpha
Classifier: Intended Audience :: Science/Research
Classifier: Topic :: Scientific/Engineering :: Artificial Intelligence
Classifier: Topic :: Software Development :: Libraries :: Python Modules
Classifier: License :: OSI Approved :: MIT License
Classifier: Programming Language :: Python :: 3.8
Classifier: Programming Language :: Python :: 3.9
Classifier: Programming Language :: Python :: 3.10
Requires-Python: >=3.8
License-File: LICENSE
Requires-Dist: dsrl
Requires-Dist: fast-safe-rl
Requires-Dist: pyrallis (==0.3.1)
Requires-Dist: pyyaml (~=6.0)
Requires-Dist: scipy (~=1.10.1)
Requires-Dist: tqdm
Requires-Dist: numpy (>1.16.0)
Requires-Dist: tensorboard (>=2.5.0)
Requires-Dist: torch (~=1.13.0)
Requires-Dist: numba (>=0.51.0)
Requires-Dist: wandb (~=0.14.0)
Requires-Dist: h5py (>=2.10.0)
Requires-Dist: protobuf (~=3.19.0)
Requires-Dist: python-dateutil (==2.8.2)
Requires-Dist: easy-runner
Requires-Dist: swig (==4.1.1)
Provides-Extra: dev
Requires-Dist: sphinx (==6.2.1) ; extra == 'dev'
Requires-Dist: sphinx-rtd-theme (==1.2.0) ; extra == 'dev'
Requires-Dist: jinja2 (==3.0.3) ; extra == 'dev'
Requires-Dist: sphinxcontrib-bibtex (==2.5.0) ; extra == 'dev'
Requires-Dist: flake8 ; extra == 'dev'
Requires-Dist: flake8-bugbear ; extra == 'dev'
Requires-Dist: yapf ; extra == 'dev'
Requires-Dist: isort ; extra == 'dev'
Requires-Dist: pytest (~=7.3.1) ; extra == 'dev'
Requires-Dist: pytest-cov (~=4.0.0) ; extra == 'dev'
Requires-Dist: networkx ; extra == 'dev'
Requires-Dist: mypy ; extra == 'dev'
Requires-Dist: pydocstyle ; extra == 'dev'
Requires-Dist: doc8 (==0.11.2) ; extra == 'dev'
Requires-Dist: scipy ; extra == 'dev'
Requires-Dist: pre-commit ; extra == 'dev'
